qstrategy-0.1.2.dist-info/METADATA
qstrategy-0.1.2.dist-info/WHEEL
qstrategy/event.py
qstrategy/dictclass.py
qstrategy/monitor.py
qstrategy/trade.py
qstrategy/base_strategy.py
qstrategy/__init__.py
qstrategy/tradecomm.py
qstrategy/py.typed
qstrategy/risk.py
qstrategy/select.py
qstrategy/broker.py
qstrategy/qstrategy.pyi
qstrategy/qstrategy.cpython-312-darwin.so
qstrategy-0.1.2.dist-info/RECORD
