Metadata-Version: 2.3
Name: qstrategy
Version: 0.1.2
Classifier: Programming Language :: Rust
Classifier: Programming Language :: Python :: Implementation :: CPython
Classifier: Programming Language :: Python :: Implementation :: PyPy
Summary: 股票个人量化交易数据策略模块
Keywords: quantitative trading,stock,rust,automatic trading
Author-email: buf1024 <buf1024@gmail.com>
Maintainer-email: buf1024 <buf1024@gmail.com>
Requires-Python: >=3.7
